bmailer/__init__.py
bmailer/async_mailer.py
bmailer/models.py
bmailer/templates.py
bmailer-0.1.1.dist-info/licenses/LICENSE-APACHE
bmailer-0.1.1.dist-info/METADATA
bmailer-0.1.1.dist-info/WHEEL
bmailer-0.1.1.dist-info/top_level.txt
bmailer-0.1.1.dist-info/RECORD
